beenpwned/__init__.py
beenpwned/beenpwned.py
beenpwned-0.1.1.dist-info/LICENSE
beenpwned-0.1.1.dist-info/METADATA
beenpwned-0.1.1.dist-info/WHEEL
beenpwned-0.1.1.dist-info/top_level.txt
beenpwned-0.1.1.dist-info/RECORD
