Metadata-Version: 2.1
Name: beenpwned
Version: 0.1.1
Summary: Check if you have been pwned
Home-page: https://github.com/rangulvers/beenpwned
Author: rangulvers
License: UNKNOWN
Project-URL: Bug Tracker, https://github.com/rangulvers/beenpwned/issues
Platform: UNKNOWN
Classifier: Programming Language :: Python :: 3
Classifier: License :: OSI Approved :: MIT License
Classifier: Operating System :: OS Independent
Requires-Python: >=3.6
License-File: LICENSE
